LICENSE
MANIFEST.in
README.md
README.rst
setup.py
ihela_oauth2_provider.egg-info/PKG-INFO
ihela_oauth2_provider.egg-info/SOURCES.txt
ihela_oauth2_provider.egg-info/dependency_links.txt
ihela_oauth2_provider.egg-info/requires.txt
ihela_oauth2_provider.egg-info/top_level.txt
ihelaprovider/__init__.py
ihelaprovider/admin.py
ihelaprovider/apps.py
ihelaprovider/base.py
ihelaprovider/models.py
ihelaprovider/provider.py
ihelaprovider/tests.py
ihelaprovider/urls.py
ihelaprovider/views.py
ihelaprovider/migrations/__init__.py